{
  "type_description_msg": {
    "type_description": {
      "type_name": "arduinobot_msgs/action/ArduinobotTask_GetResult_Response",
      "fields": [
        {
          "name": "status",
          "type": {
            "type_id": 2,
            "capacity": 0,
            "string_capacity": 0,
            "nested_type_name": ""
          },
          "default_value": ""
        },
        {
          "name": "result",
          "type": {
            "type_id": 1,
            "capacity": 0,
            "string_capacity": 0,
            "nested_type_name": "arduinobot_msgs/action/ArduinobotTask_Result"
          },
          "default_value": ""
        }
      ]
    },
    "referenced_type_descriptions": [
      {
        "type_name": "arduinobot_msgs/action/ArduinobotTask_Result",
        "fields": [
          {
            "name": "success",
            "type": {
              "type_id": 15,
              "capacity": 0,
              "string_capacity": 0,
              "nested_type_name": ""
            },
            "default_value": ""
          }
        ]
      }
    ]
  },
  "type_hashes": [
    {
      "type_name": "arduinobot_msgs/action/ArduinobotTask_GetResult_Response",
      "hash_string": "RIHS01_6d286c8e16a9560715e63f5b2a56c9b9ce2cec4417462498f9a843164eaf09b0"
    },
    {
      "type_name": "arduinobot_msgs/action/ArduinobotTask_Result",
      "hash_string": "RIHS01_c5de498d89fab912badf29174a11acddd7cd8b200c636b6ecf2953e9903f872e"
    }
  ]
}